{
  "root": [
    {
      "id": "1",
      "name": "Vegan",
      "children": [
        {
          "id": "2",
          "name": "Coconut",
          "image": "coconut.png"
        },
        {
          "name": "Almond",
          "image": "almond.png"
        }
      ],
      "lastNode": true
    },
    {
      "name": "Dairy",
      "children": [
        {
          "name": "Milk",
          "children": [
            {
              "name": "Classic",
              "children": [
                {
                  "name": "Fruit",
                  "children": [
                    {
                      "name": "Caramel apple",
                      "image": "caramel-apple.png"
                    },
                    {
                      "name": "Mango",
                      "image": "mango.png"
                    }
                  ],
                  "lastNode": true
                },
                {
                  "name": "Nut",
                  "children": [
                    {
                      "name": "Peanut butter",
                      "image": "peanut-butter.png"
                    }
                  ],
                  "lastNode": true
                },
                {
                  "name": "Coffee house",
                  "children": [
                    {
                      "name": "Chai",
                      "image": "chai.png"
                    },
                    {
                      "name": "Coffee",
                      "image": "coffee.png"
                    }
                  ],
                  "lastNode": true
                }
              ],
              "lastNode": false
            },
            {
              "name": "Adventure",
              "children": [
                {
                  "name": "Spicy",
                  "children": [
                    {
                      "name": "Bay spice",
                      "image": "bay-spice.png"
                    },
                    {
                      "name": "7 Spice",
                      "image": "7spice.png"
                    }
                  ],
                  "lastNode": true
                },
                {
                  "name": "Savory",
                  "children": [
                    {
                      "name": "Maple bacon",
                      "image": "maple-bacon.png"
                    },
                    {
                      "name": "Irish",
                      "image": "irish-stout.png"
                    }
                  ],
                  "lastNode": true
                }
              ],
              "lastNode": false
            }
          ],
          "lastNode": false
        },
        {
          "name": "Dark",
          "children": [
            {
              "name": "Classic",
              "children": [
                {
                  "name": "Fruit",
                  "children": [
                    {
                      "name": "Blueberry",
                      "image": "blueberry.png"
                    },
                    {
                      "name": "Blood orange",
                      "image": "blood-orange.png"
                    },
                    {
                      "name": "Passion fruit",
                      "image": "passionfruit.png"
                    },
                    {
                      "name": "Rasp",
                      "image": "raspberry.png"
                    }
                  ],
                  "lastNode": true
                },
                {
                  "name": "Nut",
                  "children": [
                    {
                      "name": "Hazelnut",
                      "image": "hazelnut.png"
                    },
                    {
                      "name": "Almond",
                      "image": "almond.png"
                    }
                  ],
                  "lastNode": true
                },
                {
                  "name": "Coffee house",
                  "children": [
                    {
                      "name": "Matcha",
                      "image": "matcha.png"
                    },
                    {
                      "name": "Cappacino",
                      "image": "cappucino.png"
                    },
                    {
                      "name": "Cocoa",
                      "image": "hot-cocoa.png"
                    }
                  ],
                  "lastNode": true
                },
                {
                  "name": "Sea salt",
                  "children": [
                    {
                      "name": "Sea salt",
                      "image": "sea-salt.png"
                    }
                  ],
                  "lastNode": true
                }
              ],
              "lastNode": false
            },
            {
              "name": "Adventure",
              "children": [
                {
                  "name": "Floral",
                  "children": [
                    {
                      "name": "Rose pistachio",
                      "image": "rose-pistachio.png"
                    },
                    {
                      "name": "Hibiscus cinnamon",
                      "image": "hibiscus-cinnamon.png"
                    },
                    {
                      "name": "Lavender",
                      "image": "lavender.png"
                    }
                  ],
                  "lastNode": true
                },
                {
                  "name": "Spicy",
                  "children": [
                    {
                      "name": "Spicy fig",
                      "image": "spicy-fig.png"
                    }
                  ],
                  "lastNode": true
                },
                {
                  "name": "Savory",
                  "children": [
                    {
                      "name": "Balsamic",
                      "image": "balsamic.png"
                    },
                    {
                      "name": "Rosemary",
                      "image": "rosemary.png"
                    }
                  ],
                  "lastNode": true
                }
              ],
              "lastNode": false
            }
          ],
          "lastNode": false
        }
      ],
      "lastNode": false
    }
  ]
}
